autonox/__init__.py
autonox/__main__.py
autonox/__main__.py.an
autonox/_requests.py
autonox/autonox.py
autonox/classifiers.py
autonox/config.py
autonox/constants.py
autonox/license.py
autonox/render.py
autonox/requirements.py
autonox/text.py
autonox/warn.py
autonox/templates/default/.git_archival.txt
autonox/templates/default/.gitattributes
autonox/templates/default/.gitignore
autonox/templates/default/AUTHORS.md.an
autonox/templates/default/BRANCH.md.an
autonox/templates/default/CHANGELOG.md.an
autonox/templates/default/COPYRIGHT.an
autonox/templates/default/LICENSE.an
autonox/templates/default/README.md.an
autonox/templates/default/makedirs
autonox/templates/default/noxfile.py.an
autonox/templates/default/pyproject.toml.an
autonox/templates/default/templates.json
autonox-0.1.0.dist-info/AUTHORS.md
autonox-0.1.0.dist-info/LICENSE
autonox-0.1.0.dist-info/METADATA
autonox-0.1.0.dist-info/WHEEL
autonox-0.1.0.dist-info/entry_points.txt
autonox-0.1.0.dist-info/top_level.txt
autonox-0.1.0.dist-info/RECORD
