Metadata-Version: 2.1
Name: autonox
Version: 0.1.0
Summary: Autonox is a nox wrapper for automatic project file generation.
Author-email: PyAnjel7 <PyAnjel7@gmail.com>
License: GNU General Public License v3.0 or later
Project-URL: Documentation, https://autonox.readthedocs.io
Project-URL: Repository, https://github.com/PyAnjel7/autonox.git
Project-URL: Issues, https://github.com/PyAnjel7/autonox/issues
Project-URL: Changelog, https://github.com/PyAnjel7/autonox/blob/master/CHANGELOG.md
Keywords: baseline:Reals retires.
Classifier: License :: OSI Approved :: GNU General Public License v3 or later (GPLv3+)
Classifier: Programming Language :: Python :: 3.12
Requires-Python: >=3.12
License-File: LICENSE
License-File: AUTHORS.md
Requires-Dist: GitPython>=3.1.43
Requires-Dist: Jinja2>=3.1.4
Requires-Dist: license-expression>=30.3.1
Requires-Dist: namemaker>=1.2
Requires-Dist: nox>=2024.4.15
Requires-Dist: pip>=24.2
Requires-Dist: pipreqs>=0.5.0
Requires-Dist: Requests>=2.32.3
Requires-Dist: requests-file>=2.1.0
Requires-Dist: trove-classifiers>=2024.9.12
Requires-Dist: wonderwords>=2.2.0
